ordo/__init__.py
ordo/cli.py
ordo/folder_creator.py
file_ordo-0.1.1.dist-info/METADATA
file_ordo-0.1.1.dist-info/WHEEL
file_ordo-0.1.1.dist-info/entry_points.txt
file_ordo-0.1.1.dist-info/licenses/LICENSE
file_ordo-0.1.1.dist-info/RECORD
