Metadata-Version: 2.4
Name: file-ordo
Version: 0.1.1
Summary: A cross-platform tool to create a structured file organization system
Project-URL: Homepage, https://github.com/kirklin/ordo
Project-URL: Bug Tracker, https://github.com/kirklin/ordo/issues
Author-email: Kirk Lin <linkirk@163.com>
License: GNU General Public License v3.0
License-File: LICENSE
Requires-Python: >=3.6
